pydantic_firestore/__init__.py
pydantic_firestore/document.py
pydantic_firestore/model.py
pydantic_firestore/path.py
pydantic_firestore/reference.py
pydantic_firestore/snapshot.py
pydantic_firestore/transforms.py
pydantic_firestore/utils.py
pydantic_firestore-0.5.1.dist-info/METADATA
pydantic_firestore-0.5.1.dist-info/WHEEL
pydantic_firestore-0.5.1.dist-info/licenses/LICENSE
pydantic_firestore-0.5.1.dist-info/RECORD
