Metadata-Version: 2.4
Name: pydantic_firestore
Version: 0.5.1
Summary: Pydantic models for Firestore
Project-URL: Repository, https://github.com/rostyq/pydantic-firestore
Author-email: Rostyslav Bohomaz <rostyslav.db@gmail.com>
License: MIT License
License-File: LICENSE
Keywords: firestore,pydantic
Classifier: Programming Language :: Python :: 3
Requires-Python: >=3.11
Requires-Dist: google-cloud-firestore
Requires-Dist: pydantic
